versionCompare/test.py
versionCompare/versionComparison.py
versionCompare/versionComparisonMain.py
versionCompare-0.1.2.dist-info/METADATA
versionCompare-0.1.2.dist-info/WHEEL
versionCompare-0.1.2.dist-info/top_level.txt
versionCompare-0.1.2.dist-info/RECORD
