Metadata-Version: 2.1
Name: versionCompare
Version: 0.1.2
Summary: A library to check if a number is greater, equal or less than the other.
Author: Keyur Patel
Author-email: kj8patel@uwaterloo.ca
License: MIT
Classifier: Intended Audience :: Developers
Classifier: License :: OSI Approved :: MIT License
Classifier: Programming Language :: Python
Classifier: Programming Language :: Python :: 3
Classifier: Programming Language :: Python :: 3.6
Classifier: Programming Language :: Python :: 3.7
Classifier: Programming Language :: Python :: 3.8
Classifier: Programming Language :: Python :: 3.9
Classifier: Operating System :: OS Independent
